datamagic/__init__.py
datamagic/database_converter.py
datamagic/json_converter.py
data_magic-0.1.dist-info/LICENSE
data_magic-0.1.dist-info/METADATA
data_magic-0.1.dist-info/WHEEL
data_magic-0.1.dist-info/top_level.txt
data_magic-0.1.dist-info/RECORD
