Metadata-Version: 2.1
Name: data-magic
Version: 0.1
Summary: A python library to help you import and export data from various formats easily
Home-page: https://github.com/Pythondeveloper6/Data-Magic-
Author: Mahmoud Ahmed
Author-email: contact.mahmoudahmed@gmail.com
Classifier: Programming Language :: Python :: 3
Classifier: License :: OSI Approved :: MIT License
Classifier: Operating System :: OS Independent
License-File: LICENSE
Requires-Dist: requests
Requires-Dist: pandas
